mdb_singleton/__init__.py
mdb_singleton/settings.py
mdb_singleton/singleton.py
mdb_singleton-0.1.1.dist-info/LICENSE
mdb_singleton-0.1.1.dist-info/METADATA
mdb_singleton-0.1.1.dist-info/WHEEL
mdb_singleton-0.1.1.dist-info/RECORD
