Metadata-Version: 2.1
Name: mdb-singleton
Version: 0.1.1
Summary: MongoDB connection management with thread-safe and asyncio-compatible singletons.
License: MIT
Author: nivwer
Requires-Python: >=3.11
Classifier: License :: OSI Approved :: MIT License
Classifier: Programming Language :: Python :: 3
Classifier: Programming Language :: Python :: 3.11
Classifier: Programming Language :: Python :: 3.12
Requires-Dist: asyncio (>=3.4.3)
Requires-Dist: motor (>=3.3.2)
Requires-Dist: pymongo (>=4.6.1)
Requires-Dist: python-dotenv (>=1.0.1)
